{
  "users": {
    "Test": {
      "albums": [
        {
          "id": "test1",
          "title": "Prueba",
          "emoji": ":camera:",
          "description": "Test",
          "entries": []
        }
      ]
    },
    "Neizan": {
      "albums": [
        {
          "id": "7ac8c06f-795d-47cc-9c44-522a2a8bd828",
          "title": "Recuerdos",
          "emoji": "📸",
          "description": "Álbum familiar principal para tus fotos.",
          "entries": []
        }
      ]
    }
  }
}